odoo/addons/repair_quality_control/README.rst
odoo/addons/repair_quality_control/__init__.py
odoo/addons/repair_quality_control/__manifest__.py
odoo/addons/repair_quality_control/data/repair_quality_control_data.xml
odoo/addons/repair_quality_control/i18n/ca_ES.po
odoo/addons/repair_quality_control/i18n/es.po
odoo/addons/repair_quality_control/i18n/it.po
odoo/addons/repair_quality_control/i18n/repair_quality_control.pot
odoo/addons/repair_quality_control/models/__init__.py
odoo/addons/repair_quality_control/models/qc_inspection.py
odoo/addons/repair_quality_control/models/repair.py
odoo/addons/repair_quality_control/models/res_company.py
odoo/addons/repair_quality_control/models/res_config_settings.py
odoo/addons/repair_quality_control/readme/CONTRIBUTORS.md
odoo/addons/repair_quality_control/readme/DESCRIPTION.md
odoo/addons/repair_quality_control/readme/USAGE.md
odoo/addons/repair_quality_control/static/description/icon.png
odoo/addons/repair_quality_control/static/description/icon.svg
odoo/addons/repair_quality_control/static/description/index.html
odoo/addons/repair_quality_control/tests/__init__.py
odoo/addons/repair_quality_control/tests/test_repair_quality_control.py
odoo/addons/repair_quality_control/views/qc_inspection_views.xml
odoo/addons/repair_quality_control/views/repair_views.xml
odoo/addons/repair_quality_control/views/res_config_settings_views.xml
odoo_addon_repair_quality_control-18.0.1.0.0.3.dist-info/METADATA
odoo_addon_repair_quality_control-18.0.1.0.0.3.dist-info/WHEEL
odoo_addon_repair_quality_control-18.0.1.0.0.3.dist-info/top_level.txt
odoo_addon_repair_quality_control-18.0.1.0.0.3.dist-info/RECORD
