Metadata-Version: 2.1
Name: odoo-addon-repair_quality_control
Version: 18.0.1.0.0.3
Requires-Python: >=3.10
Requires-Dist: odoo-addon-base_repair_config==18.0.*
Requires-Dist: odoo-addon-quality_control_stock_oca==18.0.*
Requires-Dist: odoo==18.0.*
Summary: Create quality controls from repair order
Home-page: https://github.com/OCA/repair
License: AGPL-3
Author: Antoni Marroig, Odoo Community Association (OCA)
Author-email: support@odoo-community.org
Classifier: Programming Language :: Python
Classifier: Framework :: Odoo
Classifier: Framework :: Odoo :: 18.0
Classifier: License :: OSI Approved :: GNU Affero General Public License v3
